<LadderDiagram>
  <Object type="PLCGraphics.DesignFile.CassView, PLCGraphics, Version=1.0.0.0, Culture=neutral, PublicKeyToken=null" name="ConvertAd">
    <Property name="Location">0, 0</Property>
    <Property name="Size">915, 2064</Property>
    <Property name="EndX">353</Property>
    <Property name="ControlAutoSize">48</Property>
  </Object>
  <Object type="ControlLibrary.Cass.JMPLD, ControlLibrary, Version=1.0.4860.28079, Culture=neutral, PublicKeyToken=null" name="jmpld1">
    <Property name="ControlSize">48</Property>
    <Property name="Location">64,1968</Property>
    <Property name="Size">192,48</Property>
    <Property name="ILRow">0</Property>
    <Property name="Content">Initial.xml</Property>
  </Object>
  <Object type="ControlLibrary.Row, ControlLibrary, Version=1.0.4860.28079, Culture=neutral, PublicKeyToken=null" name="row172">
    <Property name="ControlSize">48</Property>
    <Property name="Location">64,1728</Property>
    <Property name="Size">240,48</Property>
    <Property name="Rightdown">False</Property>
    <Property name="ILRow">0</Property>
    <Property name="Rightup">False</Property>
    <Property name="State">0</Property>
  </Object>
  <Object type="ControlLibrary.Cass.FEND, ControlLibrary, Version=1.0.4860.28079, Culture=neutral, PublicKeyToken=null" name="fend3">
    <Property name="ControlSize">48</Property>
    <Property name="Location">304,1728</Property>
    <Property name="Size">48,48</Property>
    <Property name="ILRow">74</Property>
    <Property name="DebugArrow">False</Property>
    <Property name="Comment">
    </Property>
  </Object>
  <Object type="ControlLibrary.NO, ControlLibrary, Version=1.0.4860.28079, Culture=neutral, PublicKeyToken=null" name="no34">
    <Property name="ControlSize">48</Property>
    <Property name="Location">64,1680</Property>
    <Property name="Size">48,48</Property>
    <Property name="Rightdown">False</Property>
    <Property name="DebugArrow">False</Property>
    <Property name="ILRow">70</Property>
    <Property name="Comment">
    </Property>
    <Property name="Rightup">False</Property>
    <Property name="Address">M245</Property>
    <Property name="State">0</Property>
  </Object>
  <Object type="ControlLibrary.Cass.FUNC, ControlLibrary, Version=1.0.4860.28079, Culture=neutral, PublicKeyToken=null" name="func24">
    <Property name="ControlSize">48</Property>
    <Property name="Location">160,1680</Property>
    <Property name="Size">192,48</Property>
    <Property name="Rightdown">False</Property>
    <Property name="EndArrow">true</Property>
    <Property name="DebugArrow">False</Property>
    <Property name="ILRow">72</Property>
    <Property name="Content">PresHold5()</Property>
    <Property name="Comment">
    </Property>
    <Property name="Rightup">False</Property>
    <Property name="State">0</Property>
  </Object>
  <Object type="ControlLibrary.NO, ControlLibrary, Version=1.0.4860.28079, Culture=neutral, PublicKeyToken=null" name="no29">
    <Property name="ControlSize">48</Property>
    <Property name="Location">112,1680</Property>
    <Property name="Size">48,48</Property>
    <Property name="Rightdown">False</Property>
    <Property name="DebugArrow">False</Property>
    <Property name="ILRow">71</Property>
    <Property name="Comment">使用保压五段</Property>
    <Property name="Rightup">False</Property>
    <Property name="Address">M235</Property>
    <Property name="State">0</Property>
  </Object>
  <Object type="ControlLibrary.Row, ControlLibrary, Version=1.0.4860.28079, Culture=neutral, PublicKeyToken=null" name="row150">
    <Property name="ControlSize">48</Property>
    <Property name="Location">112,960</Property>
    <Property name="Size">48,48</Property>
    <Property name="Rightdown">False</Property>
    <Property name="ILRow">0</Property>
    <Property name="Rightup">False</Property>
    <Property name="State">0</Property>
  </Object>
  <Object type="ControlLibrary.Cass.FUNC, ControlLibrary, Version=1.0.4860.28079, Culture=neutral, PublicKeyToken=null" name="func12">
    <Property name="ControlSize">48</Property>
    <Property name="Location">160,960</Property>
    <Property name="Size">192,48</Property>
    <Property name="Rightdown">False</Property>
    <Property name="EndArrow">true</Property>
    <Property name="DebugArrow">False</Property>
    <Property name="ILRow">34</Property>
    <Property name="Content">TableBack()</Property>
    <Property name="Comment">
    </Property>
    <Property name="Rightup">False</Property>
    <Property name="State">0</Property>
  </Object>
  <Object type="ControlLibrary.NO, ControlLibrary, Version=1.0.4860.28079, Culture=neutral, PublicKeyToken=null" name="no11">
    <Property name="ControlSize">48</Property>
    <Property name="Location">64,960</Property>
    <Property name="Size">48,48</Property>
    <Property name="Rightdown">False</Property>
    <Property name="DebugArrow">False</Property>
    <Property name="ILRow">33</Property>
    <Property name="Comment">座退</Property>
    <Property name="Rightup">False</Property>
    <Property name="Address">M213</Property>
    <Property name="State">0</Property>
  </Object>
  <Object type="ControlLibrary.NO, ControlLibrary, Version=1.0.4860.28079, Culture=neutral, PublicKeyToken=null" name="no12">
    <Property name="ControlSize">48</Property>
    <Property name="Location">64,912</Property>
    <Property name="Size">48,48</Property>
    <Property name="Rightdown">False</Property>
    <Property name="DebugArrow">False</Property>
    <Property name="ILRow">30</Property>
    <Property name="Comment">座进</Property>
    <Property name="Rightup">False</Property>
    <Property name="Address">M212</Property>
    <Property name="State">0</Property>
  </Object>
  <Object type="ControlLibrary.Cass.FUNC, ControlLibrary, Version=1.0.4860.28079, Culture=neutral, PublicKeyToken=null" name="func13">
    <Property name="ControlSize">48</Property>
    <Property name="Location">160,912</Property>
    <Property name="Size">192,48</Property>
    <Property name="Rightdown">False</Property>
    <Property name="EndArrow">true</Property>
    <Property name="DebugArrow">False</Property>
    <Property name="ILRow">31</Property>
    <Property name="Content">TableIn()</Property>
    <Property name="Comment">
    </Property>
    <Property name="Rightup">False</Property>
    <Property name="State">0</Property>
  </Object>
  <Object type="ControlLibrary.Row, ControlLibrary, Version=1.0.4860.28079, Culture=neutral, PublicKeyToken=null" name="row151">
    <Property name="ControlSize">48</Property>
    <Property name="Location">112,912</Property>
    <Property name="Size">48,48</Property>
    <Property name="Rightdown">False</Property>
    <Property name="ILRow">0</Property>
    <Property name="Rightup">False</Property>
    <Property name="State">0</Property>
  </Object>
  <Object type="ControlLibrary.Row, ControlLibrary, Version=1.0.4860.28079, Culture=neutral, PublicKeyToken=null" name="row149">
    <Property name="ControlSize">48</Property>
    <Property name="Location">112,816</Property>
    <Property name="Size">48,48</Property>
    <Property name="Rightdown">False</Property>
    <Property name="ILRow">0</Property>
    <Property name="Rightup">False</Property>
    <Property name="State">0</Property>
  </Object>
  <Object type="ControlLibrary.Cass.FUNC, ControlLibrary, Version=1.0.4860.28079, Culture=neutral, PublicKeyToken=null" name="func11">
    <Property name="ControlSize">48</Property>
    <Property name="Location">160,816</Property>
    <Property name="Size">192,48</Property>
    <Property name="Rightdown">False</Property>
    <Property name="EndArrow">true</Property>
    <Property name="DebugArrow">False</Property>
    <Property name="ILRow">28</Property>
    <Property name="Content">Storing()</Property>
    <Property name="Comment">
    </Property>
    <Property name="Rightup">False</Property>
    <Property name="State">0</Property>
  </Object>
  <Object type="ControlLibrary.NO, ControlLibrary, Version=1.0.4860.28079, Culture=neutral, PublicKeyToken=null" name="no10">
    <Property name="ControlSize">48</Property>
    <Property name="Location">64,816</Property>
    <Property name="Size">48,48</Property>
    <Property name="Rightdown">False</Property>
    <Property name="DebugArrow">False</Property>
    <Property name="ILRow">27</Property>
    <Property name="Comment">储料</Property>
    <Property name="Rightup">False</Property>
    <Property name="Address">M210</Property>
    <Property name="State">0</Property>
  </Object>
  <Object type="ControlLibrary.NO, ControlLibrary, Version=1.0.4860.28079, Culture=neutral, PublicKeyToken=null" name="no9">
    <Property name="ControlSize">48</Property>
    <Property name="Location">64,720</Property>
    <Property name="Size">48,48</Property>
    <Property name="Rightdown">False</Property>
    <Property name="DebugArrow">False</Property>
    <Property name="ILRow">24</Property>
    <Property name="Comment">射退</Property>
    <Property name="Rightup">False</Property>
    <Property name="Address">M207</Property>
    <Property name="State">0</Property>
  </Object>
  <Object type="ControlLibrary.Cass.FUNC, ControlLibrary, Version=1.0.4860.28079, Culture=neutral, PublicKeyToken=null" name="func10">
    <Property name="ControlSize">48</Property>
    <Property name="Location">160,720</Property>
    <Property name="Size">192,48</Property>
    <Property name="Rightdown">False</Property>
    <Property name="EndArrow">true</Property>
    <Property name="DebugArrow">False</Property>
    <Property name="ILRow">25</Property>
    <Property name="Content">InjectBack()</Property>
    <Property name="Comment">
    </Property>
    <Property name="Rightup">False</Property>
    <Property name="State">0</Property>
  </Object>
  <Object type="ControlLibrary.Row, ControlLibrary, Version=1.0.4860.28079, Culture=neutral, PublicKeyToken=null" name="row148">
    <Property name="ControlSize">48</Property>
    <Property name="Location">112,720</Property>
    <Property name="Size">48,48</Property>
    <Property name="Rightdown">False</Property>
    <Property name="ILRow">0</Property>
    <Property name="Rightup">False</Property>
    <Property name="State">0</Property>
  </Object>
  <Object type="ControlLibrary.Row, ControlLibrary, Version=1.0.4860.28079, Culture=neutral, PublicKeyToken=null" name="row147">
    <Property name="ControlSize">48</Property>
    <Property name="Location">112,672</Property>
    <Property name="Size">48,48</Property>
    <Property name="Rightdown">False</Property>
    <Property name="ILRow">0</Property>
    <Property name="Rightup">False</Property>
    <Property name="State">0</Property>
  </Object>
  <Object type="ControlLibrary.Cass.FUNC, ControlLibrary, Version=1.0.4860.28079, Culture=neutral, PublicKeyToken=null" name="func9">
    <Property name="ControlSize">48</Property>
    <Property name="Location">160,672</Property>
    <Property name="Size">192,48</Property>
    <Property name="Rightdown">False</Property>
    <Property name="EndArrow">true</Property>
    <Property name="DebugArrow">False</Property>
    <Property name="ILRow">22</Property>
    <Property name="Content">InjectIn()</Property>
    <Property name="Comment">
    </Property>
    <Property name="Rightup">False</Property>
    <Property name="State">0</Property>
  </Object>
  <Object type="ControlLibrary.NO, ControlLibrary, Version=1.0.4860.28079, Culture=neutral, PublicKeyToken=null" name="no8">
    <Property name="ControlSize">48</Property>
    <Property name="Location">64,672</Property>
    <Property name="Size">48,48</Property>
    <Property name="Rightdown">False</Property>
    <Property name="DebugArrow">False</Property>
    <Property name="ILRow">21</Property>
    <Property name="Comment">射出</Property>
    <Property name="Rightup">False</Property>
    <Property name="Address">M206</Property>
    <Property name="State">0</Property>
  </Object>
  <Object type="ControlLibrary.NO, ControlLibrary, Version=1.0.4860.28079, Culture=neutral, PublicKeyToken=null" name="no13">
    <Property name="ControlSize">48</Property>
    <Property name="Location">64,1104</Property>
    <Property name="Size">48,48</Property>
    <Property name="Rightdown">False</Property>
    <Property name="DebugArrow">False</Property>
    <Property name="ILRow">39</Property>
    <Property name="Comment">中子1退</Property>
    <Property name="Rightup">False</Property>
    <Property name="Address">M215</Property>
    <Property name="State">0</Property>
  </Object>
  <Object type="ControlLibrary.Cass.FUNC, ControlLibrary, Version=1.0.4860.28079, Culture=neutral, PublicKeyToken=null" name="func14">
    <Property name="ControlSize">48</Property>
    <Property name="Location">160,1104</Property>
    <Property name="Size">192,48</Property>
    <Property name="Rightdown">False</Property>
    <Property name="EndArrow">true</Property>
    <Property name="DebugArrow">False</Property>
    <Property name="ILRow">40</Property>
    <Property name="Content">Core1Back()</Property>
    <Property name="Comment">
    </Property>
    <Property name="Rightup">False</Property>
    <Property name="State">0</Property>
  </Object>
  <Object type="ControlLibrary.Row, ControlLibrary, Version=1.0.4860.28079, Culture=neutral, PublicKeyToken=null" name="row152">
    <Property name="ControlSize">48</Property>
    <Property name="Location">112,1104</Property>
    <Property name="Size">48,48</Property>
    <Property name="Rightdown">False</Property>
    <Property name="ILRow">0</Property>
    <Property name="Rightup">False</Property>
    <Property name="State">0</Property>
  </Object>
  <Object type="ControlLibrary.Row, ControlLibrary, Version=1.0.4860.28079, Culture=neutral, PublicKeyToken=null" name="row153">
    <Property name="ControlSize">48</Property>
    <Property name="Location">112,1056</Property>
    <Property name="Size">48,48</Property>
    <Property name="Rightdown">False</Property>
    <Property name="ILRow">0</Property>
    <Property name="Rightup">False</Property>
    <Property name="State">0</Property>
  </Object>
  <Object type="ControlLibrary.Cass.FUNC, ControlLibrary, Version=1.0.4860.28079, Culture=neutral, PublicKeyToken=null" name="func15">
    <Property name="ControlSize">48</Property>
    <Property name="Location">160,1056</Property>
    <Property name="Size">192,48</Property>
    <Property name="Rightdown">False</Property>
    <Property name="EndArrow">true</Property>
    <Property name="DebugArrow">False</Property>
    <Property name="ILRow">37</Property>
    <Property name="Content">Core1In()</Property>
    <Property name="Comment">
    </Property>
    <Property name="Rightup">False</Property>
    <Property name="State">0</Property>
  </Object>
  <Object type="ControlLibrary.NO, ControlLibrary, Version=1.0.4860.28079, Culture=neutral, PublicKeyToken=null" name="no14">
    <Property name="ControlSize">48</Property>
    <Property name="Location">64,1056</Property>
    <Property name="Size">48,48</Property>
    <Property name="Rightdown">False</Property>
    <Property name="DebugArrow">False</Property>
    <Property name="ILRow">36</Property>
    <Property name="Comment">中子1进</Property>
    <Property name="Rightup">False</Property>
    <Property name="Address">M214</Property>
    <Property name="State">0</Property>
  </Object>
  <Object type="ControlLibrary.NO, ControlLibrary, Version=1.0.4860.28079, Culture=neutral, PublicKeyToken=null" name="no15">
    <Property name="ControlSize">48</Property>
    <Property name="Location">64,1248</Property>
    <Property name="Size">48,48</Property>
    <Property name="Rightdown">False</Property>
    <Property name="DebugArrow">False</Property>
    <Property name="ILRow">45</Property>
    <Property name="Comment">中子2退</Property>
    <Property name="Rightup">False</Property>
    <Property name="Address">M217</Property>
    <Property name="State">0</Property>
  </Object>
  <Object type="ControlLibrary.Cass.FUNC, ControlLibrary, Version=1.0.4860.28079, Culture=neutral, PublicKeyToken=null" name="func16">
    <Property name="ControlSize">48</Property>
    <Property name="Location">160,1248</Property>
    <Property name="Size">192,48</Property>
    <Property name="Rightdown">False</Property>
    <Property name="EndArrow">true</Property>
    <Property name="DebugArrow">False</Property>
    <Property name="ILRow">46</Property>
    <Property name="Content">Core2Back()</Property>
    <Property name="Comment">
    </Property>
    <Property name="Rightup">False</Property>
    <Property name="State">0</Property>
  </Object>
  <Object type="ControlLibrary.Row, ControlLibrary, Version=1.0.4860.28079, Culture=neutral, PublicKeyToken=null" name="row154">
    <Property name="ControlSize">48</Property>
    <Property name="Location">112,1248</Property>
    <Property name="Size">48,48</Property>
    <Property name="Rightdown">False</Property>
    <Property name="ILRow">0</Property>
    <Property name="Rightup">False</Property>
    <Property name="State">0</Property>
  </Object>
  <Object type="ControlLibrary.NO, ControlLibrary, Version=1.0.4860.28079, Culture=neutral, PublicKeyToken=null" name="no16">
    <Property name="ControlSize">48</Property>
    <Property name="Location">64,1200</Property>
    <Property name="Size">48,48</Property>
    <Property name="Rightdown">False</Property>
    <Property name="DebugArrow">False</Property>
    <Property name="ILRow">42</Property>
    <Property name="Comment">中子2进</Property>
    <Property name="Rightup">False</Property>
    <Property name="Address">M216</Property>
    <Property name="State">0</Property>
  </Object>
  <Object type="ControlLibrary.Cass.FUNC, ControlLibrary, Version=1.0.4860.28079, Culture=neutral, PublicKeyToken=null" name="func17">
    <Property name="ControlSize">48</Property>
    <Property name="Location">160,1200</Property>
    <Property name="Size">192,48</Property>
    <Property name="Rightdown">False</Property>
    <Property name="EndArrow">true</Property>
    <Property name="DebugArrow">False</Property>
    <Property name="ILRow">43</Property>
    <Property name="Content">Core2In()</Property>
    <Property name="Comment">
    </Property>
    <Property name="Rightup">False</Property>
    <Property name="State">0</Property>
  </Object>
  <Object type="ControlLibrary.Row, ControlLibrary, Version=1.0.4860.28079, Culture=neutral, PublicKeyToken=null" name="row155">
    <Property name="ControlSize">48</Property>
    <Property name="Location">112,1200</Property>
    <Property name="Size">48,48</Property>
    <Property name="Rightdown">False</Property>
    <Property name="ILRow">0</Property>
    <Property name="Rightup">False</Property>
    <Property name="State">0</Property>
  </Object>
  <Object type="ControlLibrary.Row, ControlLibrary, Version=1.0.4860.28079, Culture=neutral, PublicKeyToken=null" name="row157">
    <Property name="ControlSize">48</Property>
    <Property name="Location">112,1344</Property>
    <Property name="Size">48,48</Property>
    <Property name="Rightdown">False</Property>
    <Property name="ILRow">0</Property>
    <Property name="Rightup">False</Property>
    <Property name="State">0</Property>
  </Object>
  <Object type="ControlLibrary.Cass.FUNC, ControlLibrary, Version=1.0.4860.28079, Culture=neutral, PublicKeyToken=null" name="func19">
    <Property name="ControlSize">48</Property>
    <Property name="Location">160,1344</Property>
    <Property name="Size">192,48</Property>
    <Property name="Rightdown">False</Property>
    <Property name="EndArrow">true</Property>
    <Property name="DebugArrow">False</Property>
    <Property name="ILRow">49</Property>
    <Property name="Content">MaleMouldBlow()</Property>
    <Property name="Comment">
    </Property>
    <Property name="Rightup">False</Property>
    <Property name="State">0</Property>
  </Object>
  <Object type="ControlLibrary.NO, ControlLibrary, Version=1.0.4860.28079, Culture=neutral, PublicKeyToken=null" name="no18">
    <Property name="ControlSize">48</Property>
    <Property name="Location">64,1344</Property>
    <Property name="Size">48,48</Property>
    <Property name="Rightdown">False</Property>
    <Property name="DebugArrow">False</Property>
    <Property name="ILRow">48</Property>
    <Property name="Comment">公模吹气</Property>
    <Property name="Rightup">False</Property>
    <Property name="Address">M222</Property>
    <Property name="State">0</Property>
  </Object>
  <Object type="ControlLibrary.NO, ControlLibrary, Version=1.0.4860.28079, Culture=neutral, PublicKeyToken=null" name="no17">
    <Property name="ControlSize">48</Property>
    <Property name="Location">64,1392</Property>
    <Property name="Size">48,48</Property>
    <Property name="Rightdown">False</Property>
    <Property name="DebugArrow">False</Property>
    <Property name="ILRow">51</Property>
    <Property name="Comment">母模吹气</Property>
    <Property name="Rightup">False</Property>
    <Property name="Address">M223</Property>
    <Property name="State">0</Property>
  </Object>
  <Object type="ControlLibrary.Cass.FUNC, ControlLibrary, Version=1.0.4860.28079, Culture=neutral, PublicKeyToken=null" name="func18">
    <Property name="ControlSize">48</Property>
    <Property name="Location">160,1392</Property>
    <Property name="Size">192,48</Property>
    <Property name="Rightdown">False</Property>
    <Property name="EndArrow">true</Property>
    <Property name="DebugArrow">False</Property>
    <Property name="ILRow">52</Property>
    <Property name="Content">FemaleMouldBlow()</Property>
    <Property name="Comment">
    </Property>
    <Property name="Rightup">False</Property>
    <Property name="State">0</Property>
  </Object>
  <Object type="ControlLibrary.Row, ControlLibrary, Version=1.0.4860.28079, Culture=neutral, PublicKeyToken=null" name="row156">
    <Property name="ControlSize">48</Property>
    <Property name="Location">112,1392</Property>
    <Property name="Size">48,48</Property>
    <Property name="Rightdown">False</Property>
    <Property name="ILRow">0</Property>
    <Property name="Rightup">False</Property>
    <Property name="State">0</Property>
  </Object>
  <Object type="ControlLibrary.NO, ControlLibrary, Version=1.0.4860.28079, Culture=neutral, PublicKeyToken=null" name="no30">
    <Property name="ControlSize">48</Property>
    <Property name="Location">64,1488</Property>
    <Property name="Size">48,48</Property>
    <Property name="Rightdown">False</Property>
    <Property name="DebugArrow">False</Property>
    <Property name="ILRow">54</Property>
    <Property name="Comment">
    </Property>
    <Property name="Rightup">False</Property>
    <Property name="Address">M241</Property>
    <Property name="State">0</Property>
  </Object>
  <Object type="ControlLibrary.NO, ControlLibrary, Version=1.0.4860.28079, Culture=neutral, PublicKeyToken=null" name="no25">
    <Property name="ControlSize">48</Property>
    <Property name="Location">112,1488</Property>
    <Property name="Size">48,48</Property>
    <Property name="Rightdown">False</Property>
    <Property name="DebugArrow">False</Property>
    <Property name="ILRow">55</Property>
    <Property name="Comment">使用保压一段</Property>
    <Property name="Rightup">False</Property>
    <Property name="Address">M231</Property>
    <Property name="State">0</Property>
  </Object>
  <Object type="ControlLibrary.Cass.FUNC, ControlLibrary, Version=1.0.4860.28079, Culture=neutral, PublicKeyToken=null" name="func20">
    <Property name="ControlSize">48</Property>
    <Property name="Location">160,1488</Property>
    <Property name="Size">192,48</Property>
    <Property name="Rightdown">False</Property>
    <Property name="EndArrow">true</Property>
    <Property name="DebugArrow">False</Property>
    <Property name="ILRow">56</Property>
    <Property name="Content">PresHold1()</Property>
    <Property name="Comment">
    </Property>
    <Property name="Rightup">False</Property>
    <Property name="State">0</Property>
  </Object>
  <Object type="ControlLibrary.NO, ControlLibrary, Version=1.0.4860.28079, Culture=neutral, PublicKeyToken=null" name="no31">
    <Property name="ControlSize">48</Property>
    <Property name="Location">64,1536</Property>
    <Property name="Size">48,48</Property>
    <Property name="Rightdown">False</Property>
    <Property name="DebugArrow">False</Property>
    <Property name="ILRow">58</Property>
    <Property name="Comment">
    </Property>
    <Property name="Rightup">False</Property>
    <Property name="Address">M242</Property>
    <Property name="State">0</Property>
  </Object>
  <Object type="ControlLibrary.NO, ControlLibrary, Version=1.0.4860.28079, Culture=neutral, PublicKeyToken=null" name="no26">
    <Property name="ControlSize">48</Property>
    <Property name="Location">112,1536</Property>
    <Property name="Size">48,48</Property>
    <Property name="Rightdown">False</Property>
    <Property name="DebugArrow">False</Property>
    <Property name="ILRow">59</Property>
    <Property name="Comment">使用保压二段</Property>
    <Property name="Rightup">False</Property>
    <Property name="Address">M232</Property>
    <Property name="State">0</Property>
  </Object>
  <Object type="ControlLibrary.Cass.FUNC, ControlLibrary, Version=1.0.4860.28079, Culture=neutral, PublicKeyToken=null" name="func21">
    <Property name="ControlSize">48</Property>
    <Property name="Location">160,1536</Property>
    <Property name="Size">192,48</Property>
    <Property name="Rightdown">False</Property>
    <Property name="EndArrow">true</Property>
    <Property name="DebugArrow">False</Property>
    <Property name="ILRow">60</Property>
    <Property name="Content">PresHold2()</Property>
    <Property name="Comment">
    </Property>
    <Property name="Rightup">False</Property>
    <Property name="State">0</Property>
  </Object>
  <Object type="ControlLibrary.Cass.FUNC, ControlLibrary, Version=1.0.4860.28079, Culture=neutral, PublicKeyToken=null" name="func23">
    <Property name="ControlSize">48</Property>
    <Property name="Location">160,1632</Property>
    <Property name="Size">192,48</Property>
    <Property name="Rightdown">False</Property>
    <Property name="EndArrow">true</Property>
    <Property name="DebugArrow">False</Property>
    <Property name="ILRow">68</Property>
    <Property name="Content">PresHold4()</Property>
    <Property name="Comment">
    </Property>
    <Property name="Rightup">False</Property>
    <Property name="State">0</Property>
  </Object>
  <Object type="ControlLibrary.NO, ControlLibrary, Version=1.0.4860.28079, Culture=neutral, PublicKeyToken=null" name="no28">
    <Property name="ControlSize">48</Property>
    <Property name="Location">112,1632</Property>
    <Property name="Size">48,48</Property>
    <Property name="Rightdown">False</Property>
    <Property name="DebugArrow">False</Property>
    <Property name="ILRow">67</Property>
    <Property name="Comment">使用保压四段</Property>
    <Property name="Rightup">False</Property>
    <Property name="Address">M234</Property>
    <Property name="State">0</Property>
  </Object>
  <Object type="ControlLibrary.NO, ControlLibrary, Version=1.0.4860.28079, Culture=neutral, PublicKeyToken=null" name="no33">
    <Property name="ControlSize">48</Property>
    <Property name="Location">64,1632</Property>
    <Property name="Size">48,48</Property>
    <Property name="Rightdown">False</Property>
    <Property name="DebugArrow">False</Property>
    <Property name="ILRow">66</Property>
    <Property name="Comment">
    </Property>
    <Property name="Rightup">False</Property>
    <Property name="Address">M244</Property>
    <Property name="State">0</Property>
  </Object>
  <Object type="ControlLibrary.NO, ControlLibrary, Version=1.0.4860.28079, Culture=neutral, PublicKeyToken=null" name="no32">
    <Property name="ControlSize">48</Property>
    <Property name="Location">64,1584</Property>
    <Property name="Size">48,48</Property>
    <Property name="Rightdown">False</Property>
    <Property name="DebugArrow">False</Property>
    <Property name="ILRow">62</Property>
    <Property name="Comment">
    </Property>
    <Property name="Rightup">False</Property>
    <Property name="Address">M243</Property>
    <Property name="State">0</Property>
  </Object>
  <Object type="ControlLibrary.NO, ControlLibrary, Version=1.0.4860.28079, Culture=neutral, PublicKeyToken=null" name="no27">
    <Property name="ControlSize">48</Property>
    <Property name="Location">112,1584</Property>
    <Property name="Size">48,48</Property>
    <Property name="Rightdown">False</Property>
    <Property name="DebugArrow">False</Property>
    <Property name="ILRow">63</Property>
    <Property name="Comment">使用保压三段</Property>
    <Property name="Rightup">False</Property>
    <Property name="Address">M233</Property>
    <Property name="State">0</Property>
  </Object>
  <Object type="ControlLibrary.Cass.FUNC, ControlLibrary, Version=1.0.4860.28079, Culture=neutral, PublicKeyToken=null" name="func22">
    <Property name="ControlSize">48</Property>
    <Property name="Location">160,1584</Property>
    <Property name="Size">192,48</Property>
    <Property name="Rightdown">False</Property>
    <Property name="EndArrow">true</Property>
    <Property name="DebugArrow">False</Property>
    <Property name="ILRow">64</Property>
    <Property name="Content">PresHold3()</Property>
    <Property name="Comment">
    </Property>
    <Property name="Rightup">False</Property>
    <Property name="State">0</Property>
  </Object>
  <Object type="ControlLibrary.Row, ControlLibrary, Version=1.0.4860.28079, Culture=neutral, PublicKeyToken=null" name="row135">
    <Property name="ControlSize">48</Property>
    <Property name="Location">208,48</Property>
    <Property name="Size">48,48</Property>
    <Property name="Rightdown">False</Property>
    <Property name="ILRow">0</Property>
    <Property name="Rightup">False</Property>
    <Property name="State">0</Property>
  </Object>
  <Object type="ControlLibrary.Cass.SPEED, ControlLibrary, Version=1.0.4860.28079, Culture=neutral, PublicKeyToken=null" name="speed1">
    <Property name="ControlSize">48</Property>
    <Property name="Location">256,48</Property>
    <Property name="Size">96,48</Property>
    <Property name="ILRow">1</Property>
    <Property name="DebugArrow">False</Property>
    <Property name="SPEEDN">K1</Property>
    <Property name="Comment">
    </Property>
  </Object>
  <Object type="ControlLibrary.Row, ControlLibrary, Version=1.0.4860.28079, Culture=neutral, PublicKeyToken=null" name="row2">
    <Property name="ControlSize">48</Property>
    <Property name="Location">64,48</Property>
    <Property name="Size">144,48</Property>
    <Property name="Rightdown">False</Property>
    <Property name="ILRow">0</Property>
    <Property name="Rightup">False</Property>
    <Property name="State">0</Property>
  </Object>
  <Object type="ControlLibrary.Row, ControlLibrary, Version=1.0.4860.28079, Culture=neutral, PublicKeyToken=null" name="row139">
    <Property name="ControlSize">48</Property>
    <Property name="Location">112,384</Property>
    <Property name="Size">48,48</Property>
    <Property name="Rightdown">False</Property>
    <Property name="ILRow">0</Property>
    <Property name="Rightup">False</Property>
    <Property name="State">0</Property>
  </Object>
  <Object type="ControlLibrary.Cass.FUNC, ControlLibrary, Version=1.0.4860.28079, Culture=neutral, PublicKeyToken=null" name="func4">
    <Property name="ControlSize">48</Property>
    <Property name="Location">160,384</Property>
    <Property name="Size">192,48</Property>
    <Property name="Rightdown">False</Property>
    <Property name="EndArrow">true</Property>
    <Property name="DebugArrow">False</Property>
    <Property name="ILRow">10</Property>
    <Property name="Content">OpenMould()</Property>
    <Property name="Comment">
    </Property>
    <Property name="Rightup">False</Property>
    <Property name="State">0</Property>
  </Object>
  <Object type="ControlLibrary.NO, ControlLibrary, Version=1.0.4860.28079, Culture=neutral, PublicKeyToken=null" name="no4">
    <Property name="ControlSize">48</Property>
    <Property name="Location">64,384</Property>
    <Property name="Size">48,48</Property>
    <Property name="Rightdown">False</Property>
    <Property name="DebugArrow">False</Property>
    <Property name="ILRow">9</Property>
    <Property name="Comment">开模启动</Property>
    <Property name="Rightup">False</Property>
    <Property name="Address">M202</Property>
    <Property name="State">0</Property>
  </Object>
  <Object type="ControlLibrary.Row, ControlLibrary, Version=1.0.4860.28079, Culture=neutral, PublicKeyToken=null" name="row138">
    <Property name="ControlSize">48</Property>
    <Property name="Location">112,240</Property>
    <Property name="Size">48,48</Property>
    <Property name="Rightdown">False</Property>
    <Property name="ILRow">0</Property>
    <Property name="Rightup">False</Property>
    <Property name="State">0</Property>
  </Object>
  <Object type="ControlLibrary.Cass.FUNC, ControlLibrary, Version=1.0.4860.28079, Culture=neutral, PublicKeyToken=null" name="func3">
    <Property name="ControlSize">48</Property>
    <Property name="Location">160,240</Property>
    <Property name="Size">192,48</Property>
    <Property name="Rightdown">False</Property>
    <Property name="EndArrow">true</Property>
    <Property name="DebugArrow">False</Property>
    <Property name="ILRow">4</Property>
    <Property name="Content">MouldAjustIn()</Property>
    <Property name="Comment">
    </Property>
    <Property name="Rightup">False</Property>
    <Property name="State">0</Property>
  </Object>
  <Object type="ControlLibrary.NO, ControlLibrary, Version=1.0.4860.28079, Culture=neutral, PublicKeyToken=null" name="no1">
    <Property name="ControlSize">48</Property>
    <Property name="Location">64,240</Property>
    <Property name="Size">48,48</Property>
    <Property name="Rightdown">False</Property>
    <Property name="DebugArrow">False</Property>
    <Property name="ILRow">3</Property>
    <Property name="Comment">调模进启动</Property>
    <Property name="Rightup">False</Property>
    <Property name="Address">M200</Property>
    <Property name="State">0</Property>
  </Object>
  <Object type="ControlLibrary.Row, ControlLibrary, Version=1.0.4860.28079, Culture=neutral, PublicKeyToken=null" name="row144">
    <Property name="ControlSize">48</Property>
    <Property name="Location">112,288</Property>
    <Property name="Size">48,48</Property>
    <Property name="Rightdown">False</Property>
    <Property name="ILRow">0</Property>
    <Property name="Rightup">False</Property>
    <Property name="State">0</Property>
  </Object>
  <Object type="ControlLibrary.Cass.FUNC, ControlLibrary, Version=1.0.4860.28079, Culture=neutral, PublicKeyToken=null" name="func6">
    <Property name="ControlSize">48</Property>
    <Property name="Location">160,288</Property>
    <Property name="Size">192,48</Property>
    <Property name="Rightdown">False</Property>
    <Property name="EndArrow">true</Property>
    <Property name="DebugArrow">False</Property>
    <Property name="ILRow">7</Property>
    <Property name="Content">MouldAjustBack()</Property>
    <Property name="Comment">
    </Property>
    <Property name="Rightup">False</Property>
    <Property name="State">0</Property>
  </Object>
  <Object type="ControlLibrary.NO, ControlLibrary, Version=1.0.4860.28079, Culture=neutral, PublicKeyToken=null" name="no5">
    <Property name="ControlSize">48</Property>
    <Property name="Location">64,288</Property>
    <Property name="Size">48,48</Property>
    <Property name="Rightdown">False</Property>
    <Property name="DebugArrow">False</Property>
    <Property name="ILRow">6</Property>
    <Property name="Comment">调模退</Property>
    <Property name="Rightup">False</Property>
    <Property name="Address">M201</Property>
    <Property name="State">0</Property>
  </Object>
  <Object type="ControlLibrary.Row, ControlLibrary, Version=1.0.4860.28079, Culture=neutral, PublicKeyToken=null" name="row140">
    <Property name="ControlSize">48</Property>
    <Property name="Location">112,432</Property>
    <Property name="Size">48,48</Property>
    <Property name="Rightdown">False</Property>
    <Property name="ILRow">0</Property>
    <Property name="Rightup">False</Property>
    <Property name="State">0</Property>
  </Object>
  <Object type="ControlLibrary.Cass.FUNC, ControlLibrary, Version=1.0.4860.28079, Culture=neutral, PublicKeyToken=null" name="func5">
    <Property name="ControlSize">48</Property>
    <Property name="Location">160,432</Property>
    <Property name="Size">192,48</Property>
    <Property name="Rightdown">False</Property>
    <Property name="EndArrow">true</Property>
    <Property name="DebugArrow">False</Property>
    <Property name="ILRow">13</Property>
    <Property name="Content">CloseMould()</Property>
    <Property name="Comment">
    </Property>
    <Property name="Rightup">False</Property>
    <Property name="State">0</Property>
  </Object>
  <Object type="ControlLibrary.NO, ControlLibrary, Version=1.0.4860.28079, Culture=neutral, PublicKeyToken=null" name="no3">
    <Property name="ControlSize">48</Property>
    <Property name="Location">64,432</Property>
    <Property name="Size">48,48</Property>
    <Property name="Rightdown">False</Property>
    <Property name="DebugArrow">False</Property>
    <Property name="ILRow">12</Property>
    <Property name="Comment">合模启动</Property>
    <Property name="Rightup">False</Property>
    <Property name="Address">M203</Property>
    <Property name="State">0</Property>
  </Object>
  <Object type="ControlLibrary.Row, ControlLibrary, Version=1.0.4860.28079, Culture=neutral, PublicKeyToken=null" name="row146">
    <Property name="ControlSize">48</Property>
    <Property name="Location">112,528</Property>
    <Property name="Size">48,48</Property>
    <Property name="Rightdown">False</Property>
    <Property name="ILRow">0</Property>
    <Property name="Rightup">False</Property>
    <Property name="State">0</Property>
  </Object>
  <Object type="ControlLibrary.Cass.FUNC, ControlLibrary, Version=1.0.4860.28079, Culture=neutral, PublicKeyToken=null" name="func8">
    <Property name="ControlSize">48</Property>
    <Property name="Location">160,528</Property>
    <Property name="Size">192,48</Property>
    <Property name="Rightdown">False</Property>
    <Property name="EndArrow">true</Property>
    <Property name="DebugArrow">False</Property>
    <Property name="ILRow">16</Property>
    <Property name="Content">DeMouldIn()</Property>
    <Property name="Comment">
    </Property>
    <Property name="Rightup">False</Property>
    <Property name="State">0</Property>
  </Object>
  <Object type="ControlLibrary.NO, ControlLibrary, Version=1.0.4860.28079, Culture=neutral, PublicKeyToken=null" name="no7">
    <Property name="ControlSize">48</Property>
    <Property name="Location">64,528</Property>
    <Property name="Size">48,48</Property>
    <Property name="Rightdown">False</Property>
    <Property name="DebugArrow">False</Property>
    <Property name="ILRow">15</Property>
    <Property name="Comment">顶进</Property>
    <Property name="Rightup">False</Property>
    <Property name="Address">M204</Property>
    <Property name="State">0</Property>
  </Object>
  <Object type="ControlLibrary.NO, ControlLibrary, Version=1.0.4860.28079, Culture=neutral, PublicKeyToken=null" name="no6">
    <Property name="ControlSize">48</Property>
    <Property name="Location">64,576</Property>
    <Property name="Size">48,48</Property>
    <Property name="Rightdown">False</Property>
    <Property name="DebugArrow">False</Property>
    <Property name="ILRow">18</Property>
    <Property name="Comment">顶退</Property>
    <Property name="Rightup">False</Property>
    <Property name="Address">M205</Property>
    <Property name="State">0</Property>
  </Object>
  <Object type="ControlLibrary.Cass.FUNC, ControlLibrary, Version=1.0.4860.28079, Culture=neutral, PublicKeyToken=null" name="func7">
    <Property name="ControlSize">48</Property>
    <Property name="Location">160,576</Property>
    <Property name="Size">192,48</Property>
    <Property name="Rightdown">False</Property>
    <Property name="EndArrow">true</Property>
    <Property name="DebugArrow">False</Property>
    <Property name="ILRow">19</Property>
    <Property name="Content">DeMouldBack()</Property>
    <Property name="Comment">
    </Property>
    <Property name="Rightup">False</Property>
    <Property name="State">0</Property>
  </Object>
  <Object type="ControlLibrary.Row, ControlLibrary, Version=1.0.4860.28079, Culture=neutral, PublicKeyToken=null" name="row145">
    <Property name="ControlSize">48</Property>
    <Property name="Location">112,576</Property>
    <Property name="Size">48,48</Property>
    <Property name="Rightdown">False</Property>
    <Property name="ILRow">0</Property>
    <Property name="Rightup">False</Property>
    <Property name="State">0</Property>
  </Object>
</LadderDiagram>